Metadata-Version: 1.0
Name: Maxitex
Version: 0.1
Summary: A tool to generate latex out of code embeded in Maxima scripts
Home-page: UNKNOWN
Author: Maxime Haselbauer
Author-email: maxime.haselbauer@googlemail.com
License: UNKNOWN
Platform: UNKNOWN
